liblaf/lime/__init__.py
liblaf/lime/__init__.pyi
liblaf/lime/__main__.py
liblaf/lime/_version.py
liblaf/lime/_version.pyi
liblaf/lime/py.typed
liblaf/lime/typing.py
liblaf/lime/cli/__init__.py
liblaf/lime/cli/__init__.pyi
liblaf/lime/cli/__main__.py
liblaf/lime/cli/_app.py
liblaf/lime/cli/_generate.py
liblaf/lime/cli/_repomix.py
liblaf/lime/cli/_commit/__init__.py
liblaf/lime/cli/_commit/__init__.pyi
liblaf/lime/cli/_commit/_commit.py
liblaf/lime/cli/_commit/_commit_type.py
liblaf/lime/cli/_commit/_interactive.py
liblaf/lime/llm/__init__.py
liblaf/lime/llm/__init__.pyi
liblaf/lime/llm/_config.py
liblaf/lime/llm/_llm.py
liblaf/lime/llm/_parse.py
liblaf/lime/prompts/commit.md
liblaf/lime/prompts/description.md
liblaf/lime/prompts/features.md
liblaf/lime/tools/__init__.py
liblaf/lime/tools/__init__.pyi
liblaf/lime/tools/_git.py
liblaf/lime/tools/_prompts.py
liblaf/lime/tools/_rich.py
liblaf/lime/tools/_xml.py
liblaf/lime/tools/constants.py
liblaf/lime/tools/_repomix/__init__.py
liblaf/lime/tools/_repomix/__init__.pyi
liblaf/lime/tools/_repomix/_invoke.py
liblaf/lime/tools/_repomix/_parse.py
liblaf_lime-0.3.16.dist-info/METADATA
liblaf_lime-0.3.16.dist-info/WHEEL
liblaf_lime-0.3.16.dist-info/entry_points.txt
liblaf_lime-0.3.16.dist-info/licenses/LICENSE
liblaf_lime-0.3.16.dist-info/RECORD
