Metadata-Version: 2.4
Name: liblaf-lime
Version: 0.3.16
Summary: 🍋‍🟩 AI-powered Git commit assistant and repository documentation generator
Project-URL: Changelog, https://github.com/liblaf/lime/blob/main/CHANGELOG.md
Project-URL: Documentation, https://liblaf.github.io/lime/
Project-URL: Homepage, https://github.com/liblaf/lime
Project-URL: Issue Tracker, https://github.com/liblaf/lime/issues
Project-URL: Release Notes, https://github.com/liblaf/lime/releases
Project-URL: Source Code, https://github.com/liblaf/lime
Author-email: liblaf <30631553+liblaf@users.noreply.github.com>
License-Expression: MIT
License-File: LICENSE
Classifier: Development Status :: 4 - Beta
Classifier: Intended Audience :: Developers
Classifier: License :: OSI Approved
Classifier: License :: OSI Approved :: MIT License
Classifier: Operating System :: OS Independent
Classifier: Programming Language :: Python
Classifier: Programming Language :: Python :: 3
Classifier: Programming Language :: Python :: 3.12
Classifier: Programming Language :: Python :: 3.13
Classifier: Programming Language :: Python :: 3.14
Classifier: Typing :: Typed
Requires-Python: >=3.12
Requires-Dist: cyclopts<5,>=4
Requires-Dist: gitmatch<0.4,>=0.3
Requires-Dist: gitpython<4,>=3
Requires-Dist: giturlparse<0.15,>=0.14
Requires-Dist: jinja2<4,>=3
Requires-Dist: lazy-loader<0.5,>=0.4
Requires-Dist: liblaf-grapes<10,>=9
Requires-Dist: litellm<2,>=1
Requires-Dist: platformdirs<5,>=4
Requires-Dist: pydantic-settings<3,>=2
Requires-Dist: pydantic<3,>=2
Requires-Dist: questionary<3,>=2
Requires-Dist: rich<15,>=14
